{
  "version": "1.1.1",
  "windows": {
    "main": {
      "main": true,
      "url": "app://editor/index.html",
      "windowType": "dockable",
      "x": 638,
      "y": 46,
      "width": 2560,
      "height": 1330,
      "layout": {
        "children": [
          {
            "children": [
              {
                "active": 0,
                "children": [
                  "hierarchy"
                ],
                "height": 431.9375,
                "type": "panel",
                "width": 609
              },
              {
                "active": 0,
                "children": [
                  "assets",
                  "cloud-function"
                ],
                "height": 814.0625,
                "type": "panel",
                "width": 609
              }
            ],
            "height": 1249,
            "type": "dock-v",
            "width": 609
          },
          {
            "children": [
              {
                "active": 0,
                "children": [
                  "scene",
                  "node-library"
                ],
                "height": 657.40625,
                "type": "panel",
                "width": 1336
              },
              {
                "active": 0,
                "children": [
                  "console",
                  "timeline",
                  "game-window"
                ],
                "height": 588.578125,
                "type": "panel",
                "width": 1336
              }
            ],
            "height": 1249,
            "type": "dock-v",
            "width": 1336
          },
          {
            "active": 0,
            "children": [
              "inspector",
              "cocos-services"
            ],
            "height": 1249,
            "type": "panel",
            "width": 609
          }
        ],
        "type": "dock-h"
      },
      "panels": [
        "hierarchy",
        "assets",
        "cloud-function",
        "scene",
        "node-library",
        "console",
        "timeline",
        "game-window",
        "inspector",
        "cocos-services"
      ]
    },
    "worker": {}
  },
  "panels": {},
  "panelLabelWidth": {
    "inspector": null
  }
}
